asyncmock/__init__.py
asyncmock/__version__.py
asyncmock-0.4.2.dist-info/LICENSE
asyncmock-0.4.2.dist-info/METADATA
asyncmock-0.4.2.dist-info/WHEEL
asyncmock-0.4.2.dist-info/top_level.txt
asyncmock-0.4.2.dist-info/RECORD
