Metadata-Version: 2.1
Name: asyncmock
Version: 0.4.2
Summary: Extension to the standard mock framework to support support async
Home-page: https://github.com/timsavage/asyncmock
Author: Tim Savage
Author-email: tim@savage.company
License: BSD-3-Clause
Keywords: testing,mock,asyncio
Platform: any
Classifier: Development Status :: 5 - Production/Stable
Classifier: Intended Audience :: Developers
Classifier: License :: OSI Approved :: BSD License
Classifier: Operating System :: OS Independent
Classifier: Programming Language :: Python :: 3.6
Classifier: Programming Language :: Python :: 3.7
Classifier: Programming Language :: Python :: 3.8
Classifier: Programming Language :: Python :: Implementation :: CPython
Classifier: Programming Language :: Python :: Implementation :: PyPy
Requires-Python: >=3.6
